xain_fl/__init__.py
xain_fl/__main__.py
xain_fl/__version__.py
xain_fl/logger.py
xain_fl/serve.py
xain_fl/config/__init__.py
xain_fl/config/cli.py
xain_fl/config/schema.py
xain_fl/coordinator/__init__.py
xain_fl/coordinator/coordinator.py
xain_fl/coordinator/coordinator_grpc.py
xain_fl/coordinator/heartbeat.py
xain_fl/coordinator/metrics_store.py
xain_fl/coordinator/participants.py
xain_fl/coordinator/round.py
xain_fl/coordinator/store.py
xain_fl/fl/__init__.py
xain_fl/fl/coordinator/__init__.py
xain_fl/fl/coordinator/aggregate.py
xain_fl/fl/coordinator/controller.py
xain_fl/tools/__init__.py
xain_fl/tools/exceptions.py
xain_fl-0.6.0.dist-info/LICENSE
xain_fl-0.6.0.dist-info/METADATA
xain_fl-0.6.0.dist-info/WHEEL
xain_fl-0.6.0.dist-info/entry_points.txt
xain_fl-0.6.0.dist-info/top_level.txt
xain_fl-0.6.0.dist-info/RECORD
