Metadata-Version: 2.1
Name: xain-fl
Version: 0.6.0
Summary: XAIN is an open source framework for federated learning.
Home-page: https://github.com/xainag/xain-fl
Author: ['XAIN AG']
Author-email: services@xain.io
License: Apache License Version 2.0
Platform: UNKNOWN
Classifier: Development Status :: 3 - Alpha
Classifier: Intended Audience :: Developers
Classifier: Intended Audience :: Information Technology
Classifier: Intended Audience :: Science/Research
Classifier: Topic :: Scientific/Engineering
Classifier: Topic :: Scientific/Engineering :: Artificial Intelligence
Classifier: Topic :: Software Development
Classifier: Topic :: Software Development :: Libraries
Classifier: Topic :: Software Development :: Libraries :: Application Frameworks
Classifier: Topic :: Software Development :: Libraries :: Python Modules
Classifier: License :: OSI Approved :: Apache Software License
Classifier: Programming Language :: Python :: 3 :: Only
Classifier: Programming Language :: Python :: 3.6
Classifier: Programming Language :: Python :: 3.7
Classifier: Programming Language :: Python :: 3.8
Classifier: Operating System :: MacOS :: MacOS X
Classifier: Operating System :: POSIX :: Linux
Requires-Python: >=3.6
Requires-Dist: numpy (==1.15)
Requires-Dist: grpcio (==1.23)
Requires-Dist: structlog (==19.2.0)
Requires-Dist: xain-proto (==0.6.0)
Requires-Dist: boto3 (==1.10.48)
Requires-Dist: toml (==0.10.0)
Requires-Dist: schema (~=0.7)
Requires-Dist: idna (==2.8)
Requires-Dist: influxdb (==5.2.3)
Requires-Dist: jsonschema (==3.2.0)
Provides-Extra: dev
Requires-Dist: black (==19.10b0) ; extra == 'dev'
Requires-Dist: mypy (==0.761) ; extra == 'dev'
Requires-Dist: pylint (==2.3.1) ; extra == 'dev'
Requires-Dist: astroid (==2.2.5) ; extra == 'dev'
Requires-Dist: isort (==4.3.21) ; extra == 'dev'
Requires-Dist: pip-licenses (==1.15.2) ; extra == 'dev'
Requires-Dist: twine (==2.0.0) ; extra == 'dev'
Requires-Dist: wheel (==0.33.6) ; extra == 'dev'
Requires-Dist: typing-extensions (==3.7.4.1) ; extra == 'dev'
Requires-Dist: pytest (==5.3.2) ; extra == 'dev'
Requires-Dist: pytest-cov (==2.8.1) ; extra == 'dev'
Requires-Dist: pytest-watch (==4.2.0) ; extra == 'dev'
Requires-Dist: pytest-mock (==2.0.0) ; extra == 'dev'
Requires-Dist: xain-sdk (==0.6.0) ; extra == 'dev'
Requires-Dist: Sphinx (==2.2.1) ; extra == 'dev'
Requires-Dist: m2r (==0.2.1) ; extra == 'dev'
Requires-Dist: sphinxcontrib-mermaid (==0.3.1) ; extra == 'dev'
Requires-Dist: sphinx-autodoc-typehints (==1.10.3) ; extra == 'dev'
Requires-Dist: docutils (<0.16) ; extra == 'dev'
Provides-Extra: docs
Requires-Dist: Sphinx (==2.2.1) ; extra == 'docs'
Requires-Dist: m2r (==0.2.1) ; extra == 'docs'
Requires-Dist: sphinxcontrib-mermaid (==0.3.1) ; extra == 'docs'
Requires-Dist: sphinx-autodoc-typehints (==1.10.3) ; extra == 'docs'
Requires-Dist: docutils (<0.16) ; extra == 'docs'
Provides-Extra: test
Requires-Dist: pytest (==5.3.2) ; extra == 'test'
Requires-Dist: pytest-cov (==2.8.1) ; extra == 'test'
Requires-Dist: pytest-watch (==4.2.0) ; extra == 'test'
Requires-Dist: pytest-mock (==2.0.0) ; extra == 'test'
Requires-Dist: xain-sdk (==0.6.0) ; extra == 'test'
